IPLA/IPLA.py
IPLA/__init__.py
IPLA-0.0.1.dist-info/METADATA
IPLA-0.0.1.dist-info/WHEEL
IPLA-0.0.1.dist-info/top_level.txt
IPLA-0.0.1.dist-info/RECORD
