Metadata-Version: 2.1
Name: IPLA
Version: 0.0.1
Summary: Incremental Probability Lottery Algorithm
Home-page: 
Author: Laogao
Author-email: 2983536011@qq.com
Classifier: Programming Language :: Python :: 3
Classifier: License :: OSI Approved :: MIT License
Classifier: Operating System :: OS Independent
Requires-Python: >=3.6
